libthumbor/__init__.py
libthumbor/crypto.py
libthumbor/django/__init__.py
libthumbor/django/urls.py
libthumbor/django/views.py
libthumbor/url.py
libthumbor/url_signers/__init__.py
libthumbor/url_signers/base64_hmac_sha1.py
libthumbor-2.0.0.dist-info/LICENSE
libthumbor-2.0.0.dist-info/WHEEL
libthumbor-2.0.0.dist-info/METADATA
libthumbor-2.0.0.dist-info/RECORD
